lumos_arm_ctl/__init__.py
lumos_arm_ctl/core/CTL_CONST.py
lumos_arm_ctl/core/Joint.py
lumos_arm_ctl/core/__init__.py
lumos_arm_ctl/core/impedance_ctl/jnt_imp_controller.py
lumos_arm_ctl/core/impedance_ctl/joint_grav_comp.py
lumos_arm_ctl/core/impedance_ctl/pin_module.py
lumos_arm_ctl/lcm/__init__.py
lumos_arm_ctl/lcm/cpp/arm_and_hand_cmd_package.hpp
lumos_arm_ctl/lcm/cpp/arm_and_hand_data_package.hpp
lumos_arm_ctl/lcm/cpp/arm_cmd_struct.hpp
lumos_arm_ctl/lcm/cpp/arm_control_cmd_lcmt.hpp
lumos_arm_ctl/lcm/cpp/arm_control_data_lcmt.hpp
lumos_arm_ctl/lcm/cpp/arm_planning_cmd_struct.hpp
lumos_arm_ctl/lcm/cpp/arm_planning_status_struct.hpp
lumos_arm_ctl/lcm/cpp/arm_sensor_struct.hpp
lumos_arm_ctl/lcm/cpp/camera_control_command_struct.hpp
lumos_arm_ctl/lcm/cpp/camera_data_struct.hpp
lumos_arm_ctl/lcm/cpp/can_debug_cmd_lcmt.hpp
lumos_arm_ctl/lcm/cpp/can_debug_data_lcmt.hpp
lumos_arm_ctl/lcm/cpp/control_parameter_request_lcmt.hpp
lumos_arm_ctl/lcm/cpp/control_parameter_respones_lcmt.hpp
lumos_arm_ctl/lcm/cpp/dcm_arm_control_lcmt.hpp
lumos_arm_ctl/lcm/cpp/dcm_com_planner_lcmt.hpp
lumos_arm_ctl/lcm/cpp/dcm_foothold_planner_lcmt.hpp
lumos_arm_ctl/lcm/cpp/dcm_gait_planner_lcmt.hpp
lumos_arm_ctl/lcm/cpp/dcm_motion_tracking_control_lcmt.hpp
lumos_arm_ctl/lcm/cpp/doll_motor_debug_cmd_struct.hpp
lumos_arm_ctl/lcm/cpp/doll_motor_debug_data_struct.hpp
lumos_arm_ctl/lcm/cpp/ecat_debug_cmd_lcmt.hpp
lumos_arm_ctl/lcm/cpp/ecat_debug_data_lcmt.hpp
lumos_arm_ctl/lcm/cpp/ecat_debug_ft_data_lcmt.hpp
lumos_arm_ctl/lcm/cpp/ecat_p3_upperbody_cmd_lcmt.hpp
lumos_arm_ctl/lcm/cpp/ecat_p3_upperbody_data_lcmt.hpp
lumos_arm_ctl/lcm/cpp/ecat_p3b_upperbody_cmd_lcmt.hpp
lumos_arm_ctl/lcm/cpp/ecat_p3b_upperbody_data_lcmt.hpp
lumos_arm_ctl/lcm/cpp/ecat_zeroerr_debug_data_lcmt.hpp
lumos_arm_ctl/lcm/cpp/hand_cmd_struct.hpp
lumos_arm_ctl/lcm/cpp/hand_debug_cmd_lcmt.hpp
lumos_arm_ctl/lcm/cpp/hand_debug_data_lcmt.hpp
lumos_arm_ctl/lcm/cpp/hand_sensor_struct.hpp
lumos_arm_ctl/lcm/cpp/height_map.hpp
lumos_arm_ctl-0.1.4.dist-info/METADATA
lumos_arm_ctl-0.1.4.dist-info/WHEEL
lumos_arm_ctl-0.1.4.dist-info/RECORD
