Metadata-Version: 2.3
Name: lumos-arm-ctl
Version: 0.1.4
Summary: lumos上位机机械臂控制
Author: yuanhuan
Author-email: 704881169@qq.com
Requires-Python: >=3.10
Classifier: Programming Language :: Python :: 3
Classifier: Programming Language :: Python :: 3.10
Classifier: Programming Language :: Python :: 3.11
Classifier: Programming Language :: Python :: 3.12
Classifier: Programming Language :: Python :: 3.13
Requires-Dist: colorlog (>=6.9.0,<7.0.0)
Requires-Dist: lcm (>=1.5.1,<2.0.0)
Requires-Dist: loop-rate-limiters (>=1.1.0,<2.0.0)
Requires-Dist: matplotlib (>=3.10.3,<4.0.0)
Requires-Dist: mujoco (>=3.3.2,<4.0.0)
Requires-Dist: numpy
Requires-Dist: pin (>=3.4.0,<4.0.0)
Requires-Dist: psutil (>=7.0.0,<8.0.0)
Requires-Dist: pynput (>=1.8.1,<2.0.0)
